mezzanine_bsbanners/__init__.py
mezzanine_bsbanners/admin.py
mezzanine_bsbanners/views.py
mezzanine_bsbanners/models.py
mezzanine_bsbanners/tests.py
mezzanine_bsbanners/settings.py
mezzanine_bsbanners/templates/bsbanners/banner.html
mezzanine_bsbanners/templatetags/__init__.py
mezzanine_bsbanners/templatetags/bsbanners_tags.py
mezzanine_bsbanners-0.1.4.dist-info/top_level.txt
mezzanine_bsbanners-0.1.4.dist-info/METADATA
mezzanine_bsbanners-0.1.4.dist-info/DESCRIPTION.rst
mezzanine_bsbanners-0.1.4.dist-info/metadata.json
mezzanine_bsbanners-0.1.4.dist-info/WHEEL
mezzanine_bsbanners-0.1.4.dist-info/RECORD
