Metadata-Version: 2.0
Name: mezzanine-bsbanners
Version: 0.1.4
Summary: 
